antichecked.py
antichecked-1.0.dist-info/LICENSE
antichecked-1.0.dist-info/WHEEL
antichecked-1.0.dist-info/METADATA
antichecked-1.0.dist-info/RECORD
