Metadata-Version: 2.1
Name: antichecked
Version: 1.0
Summary: Antichecked exceptions for Python.
Author-email: SoniEx2 <endermoneymod@gmail.com>
Project-URL: Homepage, https://ganarchy.autistic.space/project/996ab435341f148cf2c246fe800f86b8cd416506
Project-URL: Repository, https://soniex2.autistic.space/git-repos/antichecked.git
